xpathi/__init__.py
xpathi/base.py
xpathi/utils.py
xpathi/elements/__init__.py
xpathi/elements/attributes.py
xpathi/elements/custom.py
xpathi/elements/tags.py
xpathi-1.0.0.dist-info/LICENSE.txt
xpathi-1.0.0.dist-info/METADATA
xpathi-1.0.0.dist-info/WHEEL
xpathi-1.0.0.dist-info/top_level.txt
xpathi-1.0.0.dist-info/RECORD
