Metadata-Version: 2.1
Name: xpathi
Version: 1.0.0
Summary: Library for generating XPath expressions as string using magic methods 🧙✨
Home-page: https://github.com/abionics/xpathi
Author: Alex Ermolaev
Author-email: abionics.dev@gmail.com
License: MIT
Keywords: xpath scraping magic methods markup
Platform: UNKNOWN
Classifier: Programming Language :: Python :: 3
Classifier: Intended Audience :: Developers
Classifier: License :: OSI Approved :: MIT License
Classifier: Operating System :: OS Independent
Classifier: Topic :: Text Processing :: Markup
Classifier: Topic :: Text Processing :: Markup :: HTML
Classifier: Topic :: Text Processing :: Markup :: XML
Classifier: Programming Language :: Python :: 3.5
Classifier: Programming Language :: Python :: 3.6
Classifier: Programming Language :: Python :: 3.7
Classifier: Programming Language :: Python :: 3.8
Classifier: Programming Language :: Python :: 3.9
